kpn_senml
