Metadata-Version: 1.0
Name: kpn-senml
Version: 1.0.0rc3
Summary: generate and parse senml json and cbor data
Home-page: https://github.com/jan-bogaerts/slate
Author: Jan Bogaerts
Author-email: jb@elastetic.com
License: APACHE
Keywords: senml kpn cbor json
Platform: UNKNOWN
